mqss_client-0.2.1.dist-info/METADATA
mqss_client-0.2.1.dist-info/WHEEL
mqss_client-0.2.1.dist-info/entry_points.txt
mqss_client-0.2.1.dist-info/licenses/LICENSE
mqss_client/__init__.py
mqss_client/base_client.py
mqss_client/comm/rmq_client.py
mqss_client/hpc_client.py
mqss_client/job.py
mqss_client/mqss_client.py
mqss_client/resource_info.py
mqss_client/rest_client.py
mqss_client/settings.py
mqss_client-0.2.1.dist-info/RECORD
