Metadata-Version: 2.1
Name: mqss-client
Version: 0.2.1
Summary: A client for MQP and HPCQC
Author-Email: mqss <mqss@munich-quantum-valley.de>
License: Apache-2.0
Requires-Python: >=3.8
Requires-Dist: requests>=2.31.0
Requires-Dist: python-decouple>=3.8
Requires-Dist: pika>=1.3.2
